readableID/__init__.py
readableID-0.0.4.dist-info/DESCRIPTION.rst
readableID-0.0.4.dist-info/METADATA
readableID-0.0.4.dist-info/RECORD
readableID-0.0.4.dist-info/WHEEL
readableID-0.0.4.dist-info/metadata.json
readableID-0.0.4.dist-info/top_level.txt
