Metadata-Version: 2.0
Name: readableID
Version: 0.0.4
Summary: Transform integer ids into readable, nonconsecutive ids
Home-page: http://github.com/nziehn/readableID
Author: Nils Ziehn
Author-email: nziehn@mail.com
License: MIT
Platform: UNKNOWN
